aws_monitoring/__init__.py
aws_monitoring/config.py
aws_monitoring/utils.py
aws_monitoring/org/__init__.py
aws_monitoring/org/utils.py
aws_monitor-1.0.1.dist-info/LICENSE
aws_monitor-1.0.1.dist-info/METADATA
aws_monitor-1.0.1.dist-info/WHEEL
aws_monitor-1.0.1.dist-info/entry_points.txt
aws_monitor-1.0.1.dist-info/top_level.txt
aws_monitor-1.0.1.dist-info/RECORD
