Metadata-Version: 2.1
Name: aws-monitor
Version: 1.0.1
Summary: A package for monitoring AWS resources
Home-page: https://github.com/Theemiss/aws_monitor
Author: Ahmed Belhaj
Author-email: ahmedbelhaj.it@gmail.com
License: UNKNOWN
Platform: UNKNOWN
Classifier: Programming Language :: Python :: 3
Classifier: License :: OSI Approved :: MIT License
Classifier: Operating System :: OS Independent
Requires-Python: >=3.8
Requires-Dist: boto3
Requires-Dist: matplotlib
